prism_ole_handler/__init__.py
prism_ole_handler/cli/__init__.py
prism_ole_handler/cli/extract.py
prism_ole_handler/cli/insert.py
prism_ole_handler/core/__init__.py
prism_ole_handler/core/extractor.py
prism_ole_handler/core/inserter.py
prism_ole_handler/test/test_01.pptx
prism_ole_handler/test/test_01.prism
prism_ole_handler/test/test_01.pzfx
prism_ole_handler/utils/__init__.py
prism_ole_handler/utils/ole_builder.py
prism_ole_handler-0.1.1.dist-info/licenses/LICENSE
prism_ole_handler-0.1.1.dist-info/METADATA
prism_ole_handler-0.1.1.dist-info/WHEEL
prism_ole_handler-0.1.1.dist-info/entry_points.txt
prism_ole_handler-0.1.1.dist-info/top_level.txt
prism_ole_handler-0.1.1.dist-info/RECORD
