Metadata-Version: 2.4
Name: prism-ole-handler
Version: 0.1.1
Summary: Extract and insert GraphPad PRISM objects from Microsoft Office documents (PowerPoint, Word, Excel) on macOS
Home-page: https://github.com/armish/prism-ole-handler
Author: B. Arman Aksoy
Author-email: "B. Arman Aksoy" <arman@aksoy.org>
Project-URL: Homepage, https://github.com/armish/prism-ole-handler
Project-URL: Bug Reports, https://github.com/armish/prism-ole-handler/issues
Project-URL: Source, https://github.com/armish/prism-ole-handler
Keywords: prism,ole,handler,microsoft,office,powerpoint,word,excel,macos,graphpad
Classifier: Development Status :: 4 - Beta
Classifier: Intended Audience :: Science/Research
Classifier: License :: OSI Approved :: MIT License
Classifier: Operating System :: MacOS
Classifier: Programming Language :: Python :: 3
Classifier: Programming Language :: Python :: 3.9
Classifier: Programming Language :: Python :: 3.10
Classifier: Programming Language :: Python :: 3.11
Classifier: Programming Language :: Python :: 3.12
Classifier: Topic :: Scientific/Engineering
Classifier: Topic :: Office/Business :: Office Suites
Requires-Python: >=3.9
License-File: LICENSE
Requires-Dist: olefile>=0.46
Provides-Extra: dev
Requires-Dist: pytest>=6.0; extra == "dev"
Requires-Dist: pytest-cov>=2.0; extra == "dev"
Requires-Dist: black>=22.0; extra == "dev"
Requires-Dist: flake8>=4.0; extra == "dev"
Requires-Dist: mypy>=0.950; extra == "dev"
Requires-Dist: build>=0.8; extra == "dev"
Requires-Dist: twine>=4.0; extra == "dev"
Dynamic: author
Dynamic: home-page
Dynamic: license-file
Dynamic: requires-python
